leaf/__init__.py
leaf/__main__.py
leafQR-0.0.1.dist-info/LICENSE
leafQR-0.0.1.dist-info/METADATA
leafQR-0.0.1.dist-info/WHEEL
leafQR-0.0.1.dist-info/entry_points.txt
leafQR-0.0.1.dist-info/top_level.txt
leafQR-0.0.1.dist-info/RECORD
