Metadata-Version: 2.1
Name: leafQR
Version: 0.0.1
Summary: A Simple Qr-Code Generator
Home-page: https://github.com/newtoallofthis123/leaf
Author: NoobScience
Author-email: noobscience123@gmail.com
License: MIT
Project-URL: Author WebSite, https://newtoallofthis123.github.io/About
Project-URL: Bug Tracker, https://github.com/newtoallofthis123/leaf/issues
Platform: UNKNOWN
Classifier: License :: OSI Approved :: MIT License
Classifier: Programming Language :: Python :: 3
Classifier: Programming Language :: Python :: 3.7
Requires-Python: >=3.6
License-File: LICENSE
Requires-Dist: PyQRCode
Requires-Dist: pypng
